tsakul/__init__.py
tsakul/_context.py
tsakul/assignments.py
tsakul/csr.py
tsakul/demand.py
tsakul/demand_data.py
tsakul/graph_utils.py
tsakul/results.py
tsakul/settings.py
tsakul/supply.py
tsakul/supply_data.py
tsakul/utilities.py
tsakul/visualization.py
tsakul/dta/__init__.py
tsakul/dta/aon.py
tsakul/dta/debugging.py
tsakul/dta/deterministic.py
tsakul/dta/dynamic_dijkstra.py
tsakul/dta/i_ltm.py
tsakul/dta/i_ltm_aon.py
tsakul/dta/i_ltm_cls.py
tsakul/dta/i_ltm_setup.py
tsakul/dta/incremental_assignment.py
tsakul/dta/orca_nodel_model.py
tsakul/dta/qr_projection.py
tsakul/dta/travel_times.py
tsakul/sta/__init__.py
tsakul/sta/_debugging_sta.py
tsakul/sta/dial_b.py
tsakul/sta/dial_stochastic_assignment.py
tsakul/sta/dun.py
tsakul/sta/equilibrate_bush.py
tsakul/sta/gap.py
tsakul/sta/msa.py
tsakul/sta/uncongested_dial.py
tsakul/sta/utilities.py
tsakul/toy_networks/birmingham_net.tntp
tsakul/toy_networks/birmingham_node.tntp
tsakul/toy_networks/chicagoregional_net.tntp
tsakul/toy_networks/chicagoregional_node.tntp
tsakul/toy_networks/chicagosketch_net.tntp
tsakul/toy_networks/chicagosketch_node.tntp
tsakul/toy_networks/siouxfalls_net.tntp
tsakul/toy_networks/siouxfalls_node.tntp
tsacib-0.2.6.dist-info/LICENSE.txt
tsacib-0.2.6.dist-info/METADATA
tsacib-0.2.6.dist-info/WHEEL
tsacib-0.2.6.dist-info/top_level.txt
tsacib-0.2.6.dist-info/RECORD
